webbot/__init__.py
webbot/webbot.py
oronium-1.0.11.dist-info/LICENSE
oronium-1.0.11.dist-info/METADATA
oronium-1.0.11.dist-info/WHEEL
oronium-1.0.11.dist-info/entry_points.txt
oronium-1.0.11.dist-info/RECORD
