Metadata-Version: 2.1
Name: oronium
Version: 1.0.11
Summary: Webbot selenium driver for testing openremote
Home-page: https://github.com/aktur/webbot
License: AGPLv3
Keywords: webbot,selenium,chromium
Author: Michal Rutka
Author-email: michal@openremote.io
Maintainer: Michal
Maintainer-email: michal@openremote.io
Requires-Python: >=3.7,<4.0
Classifier: License :: Other/Proprietary License
Classifier: Programming Language :: Python :: 3
Classifier: Programming Language :: Python :: 3.7
Classifier: Programming Language :: Python :: 3.8
Classifier: Programming Language :: Python :: 3.9
Classifier: Programming Language :: Python :: 3.10
Classifier: Programming Language :: Python :: 3.11
Classifier: Programming Language :: Python :: 3.12
Requires-Dist: selenium (>=3.141.0,<4.0.0)
Requires-Dist: urllib3 (==1.26.14)
Requires-Dist: webdriver-manager (==4.0.1)
Project-URL: Repository, https://github.com/aktur/webbot
